red_aluminum/__init__.py
red_aluminum-0.0.1.dist-info/entry_points.txt
red_aluminum-0.0.1.dist-info/licenses/LICENSE
red_aluminum-0.0.1.dist-info/WHEEL
red_aluminum-0.0.1.dist-info/METADATA
red_aluminum-0.0.1.dist-info/RECORD
